marimograd/__init__.py
marimograd/export.py
marimograd-0.0.3.dist-info/METADATA
marimograd-0.0.3.dist-info/WHEEL
marimograd-0.0.3.dist-info/entry_points.txt
marimograd-0.0.3.dist-info/licenses/LICENSE
marimograd-0.0.3.dist-info/RECORD
