Metadata-Version: 2.4
Name: marimograd
Version: 0.0.3
Summary: Export marimo notebooks in style
Project-URL: repository, https://github.com/tschm/marimograd
Author-email: Thomas Schmelzer <thomas.schmelzer@gmail.com>
License-File: LICENSE
Requires-Python: >=3.10
Requires-Dist: fire>=0.7.0
Requires-Dist: jinja2>=3.1.6
Requires-Dist: loguru>=0.7.3
